switcher/__init__.py
switcher/publisher.py
switcher/test.py
switcher-0.1.8.dist-info/LICENSE
switcher-0.1.8.dist-info/METADATA
switcher-0.1.8.dist-info/WHEEL
switcher-0.1.8.dist-info/top_level.txt
switcher-0.1.8.dist-info/RECORD
