Metadata-Version: 2.1
Name: switcher
Version: 0.1.8
Summary: python SDK for switch service to publish messages on topics
Home-page: https://github.com/Kareem-Emad/switch-py
Author: Kareem Emad
Author-email: kareememad400@gmail.com
License: MIT
Download-URL: https://pypi.org/project/switcher/
Keywords: pubsub,events
Platform: UNKNOWN
Requires-Dist: requests (==2.24.0)
Requires-Dist: pyjwt (==1.7.1)
